ChunkUpload/__init__.py
ChunkUpload/asgi.py
ChunkUpload/settings.py
ChunkUpload/urls.py
ChunkUpload/wsgi.py
chunk_upload/__init__.py
chunk_upload/admin.py
chunk_upload/apps.py
chunk_upload/cron.py
chunk_upload/models.py
chunk_upload/serializers.py
chunk_upload/signals.py
chunk_upload/tests.py
chunk_upload/urls.py
chunk_upload/views.py
chunk_upload/migrations/0001_initial.py
chunk_upload/migrations/__init__.py
tests/__init__.py
tests/test_views.py
ChunkUpload-0.3.2.dist-info/LICENSE
ChunkUpload-0.3.2.dist-info/METADATA
ChunkUpload-0.3.2.dist-info/WHEEL
ChunkUpload-0.3.2.dist-info/top_level.txt
ChunkUpload-0.3.2.dist-info/RECORD
