Metadata-Version: 2.1
Name: ChunkUpload
Version: 0.3.2
Summary: A django app for uploading videos chunk by chunk and completing uploaded chunk after all chunks have been uploaded.
Home-page: https://github.com/MOQA14
Author-email: mamad.agha750202@gmail.com
License: MIT
Classifier: Development Status :: 4 - Beta
Classifier: Environment :: Web Environment
Classifier: Programming Language :: Python :: 3
Classifier: Programming Language :: Python :: 3.6
Classifier: Programming Language :: Python :: 3.7
Classifier: Programming Language :: Python :: 3.8
Classifier: Programming Language :: Python :: 3.9
Classifier: Programming Language :: Python :: 3.10
Classifier: Programming Language :: Python :: 3.11
Classifier: License :: OSI Approved :: MIT License
Classifier: Operating System :: OS Independent
License-File: LICENSE
Requires-Dist: django>=3.0
